libcomps/__init__.py
libcomps/_libpycomps.so
libcomps.libs/liblzma-51a76f52.so.5.2.4
libcomps.libs/libxml2-39f609e7.so.2.9.7
libcomps-0.1.23.post1.dist-info/METADATA
libcomps-0.1.23.post1.dist-info/WHEEL
libcomps-0.1.23.post1.dist-info/top_level.txt
libcomps-0.1.23.post1.dist-info/RECORD
libcomps-0.1.23.post1.dist-info/licenses/COPYING
